icoscp_core/__init__.py
icoscp_core/auth.py
icoscp_core/bootstrap.py
icoscp_core/cities.py
icoscp_core/cpb.py
icoscp_core/dataclient.py
icoscp_core/envri.py
icoscp_core/geofeaturemeta.py
icoscp_core/http.py
icoscp_core/icos.py
icoscp_core/metaclient.py
icoscp_core/metacore.py
icoscp_core/portaluse_client.py
icoscp_core/py.typed
icoscp_core/rolemeta.py
icoscp_core/sites.py
icoscp_core/sparql.py
icoscp_core/queries/cpbmeta.py
icoscp_core/queries/dataobjlist.py
icoscp_core/queries/py.typed
icoscp_core/queries/speclist.py
icoscp_core/queries/stationlist.py
icoscp_core-0.3.11.dist-info/licenses/LICENSE
icoscp_core-0.3.11.dist-info/WHEEL
icoscp_core-0.3.11.dist-info/METADATA
icoscp_core-0.3.11.dist-info/RECORD
