Metadata-Version: 2.4
Name: icoscp_core
Version: 0.3.11
Summary: icoscp_core
Keywords: environment,research,infrastructure,data access
Author-email: Oleg Mirzov <oleg.mirzov@nateko.lu.se>
Maintainer-email: Jonathan Schenk <jonathan.schenk@nateko.lu.se>, Zois Zogopoulos <zois.zogopoulos@nateko.lu.se>, Oleg Mirzov <oleg.mirzov@nateko.lu.se>
Requires-Python: >=3.10
Classifier: License :: OSI Approved :: GNU General Public License v3 or later (GPLv3+)
License-File: LICENSE
Requires-Dist: dacite==1.8.1
Requires-Dist: numpy>=1.23
Project-URL: Source, https://github.com/ICOS-Carbon-Portal/data/tree/master/src/main/python/icoscp_core
